{
  "objectInfo" : {
    "id" : "9gpTgYdRsLvcCdnTXhFmKW",
    "name" : "Shashank",
    "type" : "Project",
    "metadata" : {
      "modelVersion" : {
        "major" : 0,
        "minor" : 0
      },
      "repoInfo" : null,
      "contextAttributes" : [ ],
      "additionalInfo" : {
        "description" : "",
        "contentType" : "Binary",
        "documentState" : "COMPLETE"
      }
    }
  },
  "dataFileExtension" : "json",
  "updateTime" : "2024-05-30T09:19:57.628Z",
  "objectRefs" : [ ]
}